flat_table/__init__.py
flat_table/_norm.py
flat_table/_version.py
flat_table-1.1.1.dist-info/LICENSE
flat_table-1.1.1.dist-info/METADATA
flat_table-1.1.1.dist-info/WHEEL
flat_table-1.1.1.dist-info/top_level.txt
flat_table-1.1.1.dist-info/RECORD
