Metadata-Version: 2.1
Name: flat-table
Version: 1.1.1
Summary: A broader implementation of pandas json_normalize function.
Home-page: https://github.com/metinsenturk/flat_table
Author: Metin Senturk
Author-email: metinsenturk@me.com
License: MIT
Keywords: pandas,json_normalize,dict_to_columns,flatten
Platform: UNKNOWN
Classifier: Programming Language :: Python :: 3
Classifier: License :: OSI Approved :: MIT License
Classifier: Operating System :: OS Independent
Classifier: Intended Audience :: Developers
Classifier: Topic :: Scientific/Engineering :: Information Analysis
Requires-Python: >=3.6
Requires-Dist: pandas
Requires-Dist: numpy
